crudatalab/__init__.py
crudatalab/api_client.py
crudatalab/api_config.py
crudatalab/api_definitions.py
crudatalab/api_definitions_search.py
crudatalab/api_definitions_sema.py
crudatalab/data_reader.py
crudatalab/upload_frame.py
crudatalab/view_definitions.py
crudatalab-1.3.1.dist-info/LICENSE
crudatalab-1.3.1.dist-info/METADATA
crudatalab-1.3.1.dist-info/WHEEL
crudatalab-1.3.1.dist-info/top_level.txt
crudatalab-1.3.1.dist-info/RECORD
