Metadata-Version: 2.2
Name: crudatalab
Version: 1.3.1
Summary: Official Python package for CRU DataLab's API
Home-page: https://github.com/crugroup/cru-datalab
Author: CRU International Limited
Author-email: CRU Internaional <alex.kulikov@crugroup.com>
License: MIT License
Project-URL: Homepage, https://github.com/crugroup/cru-datalab
Project-URL: Repository, https://github.com/crugroup/cru-datalab.git
Project-URL: Issues, https://github.com/crugroup/cru-datalab/issues      
Keywords: API,crudatalab
Classifier: Programming Language :: Python :: 3 :: Only
Classifier: License :: OSI Approved :: MIT License
Classifier: Development Status :: 5 - Production/Stable
Classifier: Operating System :: OS Independent
Requires-Python: >=3.9
License-File: LICENSE
Requires-Dist: pandas>=2.0.0
Requires-Dist: pytest-shutil==1.7.0
Dynamic: author
Dynamic: home-page
